{
  "app_name": "8a381dbf6e02470a8114a28fcb4ac703",
  "app_title": "Awaken",
  "asset_infos": {
    "Windows": {
      "app_name": "8a381dbf6e02470a8114a28fcb4ac703",
      "asset_id": "8a381dbf6e02470a8114a28fcb4ac703",
      "build_version": "0.1.7",
      "catalog_item_id": "d9d7fc60ea034b239095e1cf26fc997b",
      "label_name": "Live-Windows",
      "metadata": {
        "installationPoolId": "0e22b1ca464a4ac7b67c4f1b3e9c5872"
      },
      "namespace": "879a4b6564b4491e9f523c634d181756",
      "sidecar_rev": 0
    }
  },
  "base_urls": [],
  "metadata": {
    "applicationId": "fghi4567C8CX3xSycC4zQWOBGMxQPEXp",
    "categories": [
      {
        "path": "games"
      },
      {
        "path": "applications"
      }
    ],
    "creationDate": "2023-11-29T03:33:59.878Z",
    "customAttributes": {
      "FolderName": {
        "type": "STRING",
        "value": "Awaken"
      }
    },
    "description": "Awaken",
    "developer": "Polrare Lab",
    "developerId": "o-z9ce6yzh2g6tvz7pcuv6qqcgxuusje",
    "endOfSupport": false,
    "entitlementName": "d9d7fc60ea034b239095e1cf26fc997b",
    "entitlementType": "EXECUTABLE",
    "id": "d9d7fc60ea034b239095e1cf26fc997b",
    "itemType": "DURABLE",
    "keyImages": [
      {
        "alt": "Awaken Offer",
        "height": 1440,
        "md5": "63d95b1adf57c2305641c281021a6283",
        "size": 3033916,
        "type": "DieselGameBox",
        "uploadedDate": "2024-01-03T04:22:54.803Z",
        "url": "https://cdn1.epicgames.com/spt-assets/fe66ae5aeb1a4198a36dcaffdfd70f13/awaken-jdpe1.jpg",
        "width": 2560
      },
      {
        "alt": "Download Awaken Offer",
        "height": 1600,
        "md5": "38ffbc030b65d341d8be306dfee02325",
        "size": 2341200,
        "type": "DieselGameBoxTall",
        "uploadedDate": "2023-12-12T10:19:02.364Z",
        "url": "https://cdn1.epicgames.com/spt-assets/fe66ae5aeb1a4198a36dcaffdfd70f13/awaken-1lija.png",
        "width": 1200
      }
    ],
    "lastModifiedDate": "2024-11-04T13:45:56.357Z",
    "mainGameItemList": [],
    "namespace": "879a4b6564b4491e9f523c634d181756",
    "releaseInfo": [
      {
        "appId": "8a381dbf6e02470a8114a28fcb4ac703",
        "id": "ba02f39167ee4d91903908bf51fcc144",
        "platform": [
          "Windows"
        ]
      }
    ],
    "requiresSecureAccount": false,
    "status": "ACTIVE",
    "title": "Awaken",
    "unsearchable": false
  },
  "sidecar": null
}