{
  "app_name": "a3fe29481a014a3a85b87c6a41c5697f",
  "app_title": "Raid Shadow Legends",
  "asset_infos": {
    "Windows": {
      "app_name": "a3fe29481a014a3a85b87c6a41c5697f",
      "asset_id": "a3fe29481a014a3a85b87c6a41c5697f",
      "build_version": "1.0.276",
      "catalog_item_id": "c90ad90431de4cc7b931fffb67a8f254",
      "label_name": "Live-Windows",
      "metadata": {
        "installationPoolId": "720c468776484957a0f32f9bf0812512"
      },
      "namespace": "f42ad298a6c84ee284dd45995e14ba3c",
      "sidecar_rev": 0
    }
  },
  "base_urls": [],
  "metadata": {
    "applicationId": "",
    "categories": [
      {
        "path": "games"
      },
      {
        "path": "applications"
      }
    ],
    "creationDate": "2022-01-25T09:33:12.246Z",
    "customAttributes": {
      "FolderName": {
        "type": "STRING",
        "value": "RaidShadowLegends"
      }
    },
    "description": "Raid",
    "developer": "Plarium Global",
    "developerId": "o-h66ch3ram2me5j33eu297mq85bk6lz",
    "endOfSupport": false,
    "entitlementName": "c90ad90431de4cc7b931fffb67a8f254",
    "entitlementType": "EXECUTABLE",
    "id": "c90ad90431de4cc7b931fffb67a8f254",
    "itemType": "DURABLE",
    "keyImages": [
      {
        "alt": "Raid Shadow Legends Offer",
        "height": 1440,
        "md5": "fb5790f137d970316db6312d87762ca5",
        "size": 2365688,
        "type": "DieselGameBox",
        "uploadedDate": "2025-08-21T12:17:09.919Z",
        "url": "https://cdn1.epicgames.com/spt-assets/1ba2e5e0fff34e108b99ff2cc5d0d0f7/raid-shadow-legends-1mqhz.png",
        "width": 2560
      },
      {
        "alt": "Download Raid Shadow Legends Offer",
        "height": 1600,
        "md5": "2a4c1e1d8582ace504fc56209084b37b",
        "size": 2845563,
        "type": "DieselGameBoxTall",
        "uploadedDate": "2025-08-21T12:17:15.680Z",
        "url": "https://cdn1.epicgames.com/spt-assets/1ba2e5e0fff34e108b99ff2cc5d0d0f7/raid-shadow-legends-16s7b.png",
        "width": 1200
      }
    ],
    "lastModifiedDate": "2025-08-21T12:49:51.694Z",
    "mainGameItemList": [],
    "namespace": "f42ad298a6c84ee284dd45995e14ba3c",
    "releaseInfo": [
      {
        "appId": "a3fe29481a014a3a85b87c6a41c5697f",
        "id": "9a42de9eba9d4d01b08d041bd525ee91",
        "platform": [
          "Windows"
        ]
      }
    ],
    "requiresSecureAccount": false,
    "status": "ACTIVE",
    "title": "Raid Shadow Legends",
    "unsearchable": false
  },
  "sidecar": null
}